nlu/__init__.py
nlu/info.py
nlu/namespace.py
nlu/pipe_components.py
nlu/pipeline.py
nlu/components/__init__.py
nlu/components/classifier.py
nlu/components/embedding.py
nlu/components/labeled_dependency_parser.py
nlu/components/lemmatizer.py
nlu/components/normalizer.py
nlu/components/sentence_detector.py
nlu/components/spell_checker.py
nlu/components/stemmer.py
nlu/components/tokenizer.py
nlu/components/unlabeled_dependency_parser.py
nlu/components/util.py
nlu/components/classifiers/__init__.py
nlu/components/classifiers/classifier_dl/__init__.py
nlu/components/classifiers/classifier_dl/classifier_dl.py
nlu/components/classifiers/language_detector/__init__.py
nlu/components/classifiers/language_detector/language_detector.py
nlu/components/classifiers/named_entity_recognizer_crf/__init__.py
nlu/components/classifiers/named_entity_recognizer_crf/ner_crf.py
nlu/components/classifiers/ner/__init__.py
nlu/components/classifiers/ner/ner_dl.py
nlu/components/classifiers/pos/__init__.py
nlu/components/classifiers/pos/part_of_speech_jsl.py
nlu/components/classifiers/sentiment_detector/__init__.py
nlu/components/classifiers/sentiment_detector/sentiment_detector.py
nlu/components/classifiers/sentiment_dl/__init__.py
nlu/components/classifiers/sentiment_dl/sentiment_dl.py
nlu/components/classifiers/vivekn_sentiment/__init__.py
nlu/components/classifiers/vivekn_sentiment/vivekn_sentiment_detector.py
nlu/components/dependency_typeds/__init__.py
nlu/components/dependency_typeds/labeled_dependency_parser/__init__.py
nlu/components/dependency_typeds/labeled_dependency_parser/labeled_dependency_parser.py
nlu/components/dependency_untypeds/__init__.py
nlu/components/dependency_untypeds/unlabeled_dependency_parser/__init__.py
nlu/components/dependency_untypeds/unlabeled_dependency_parser/unlabeled_dependency_parser.py
nlu/components/embeddings/__init__.py
nlu/components/embeddings/albert/__init__.py
nlu/components/embeddings/albert/spark_nlp_albert.py
peanutbuterdatatime2-0.0.2.dist-info/LICENSE
peanutbuterdatatime2-0.0.2.dist-info/METADATA
peanutbuterdatatime2-0.0.2.dist-info/WHEEL
peanutbuterdatatime2-0.0.2.dist-info/top_level.txt
peanutbuterdatatime2-0.0.2.dist-info/RECORD
